odoo/addons/stock_picking_product_assortment/README.rst
odoo/addons/stock_picking_product_assortment/__init__.py
odoo/addons/stock_picking_product_assortment/__manifest__.py
odoo/addons/stock_picking_product_assortment/i18n/es.po
odoo/addons/stock_picking_product_assortment/i18n/it.po
odoo/addons/stock_picking_product_assortment/i18n/nl.po
odoo/addons/stock_picking_product_assortment/i18n/stock_picking_product_assortment.pot
odoo/addons/stock_picking_product_assortment/models/__init__.py
odoo/addons/stock_picking_product_assortment/models/stock_picking.py
odoo/addons/stock_picking_product_assortment/readme/CONFIGURE.md
odoo/addons/stock_picking_product_assortment/readme/CONTRIBUTORS.md
odoo/addons/stock_picking_product_assortment/readme/DESCRIPTION.md
odoo/addons/stock_picking_product_assortment/readme/USAGE.md
odoo/addons/stock_picking_product_assortment/static/description/icon.png
odoo/addons/stock_picking_product_assortment/static/description/index.html
odoo/addons/stock_picking_product_assortment/tests/__init__.py
odoo/addons/stock_picking_product_assortment/tests/test_stock_picking_product_assortment.py
odoo/addons/stock_picking_product_assortment/views/stock_picking_view.xml
odoo_addon_stock_picking_product_assortment-18.0.1.0.0.9.dist-info/METADATA
odoo_addon_stock_picking_product_assortment-18.0.1.0.0.9.dist-info/WHEEL
odoo_addon_stock_picking_product_assortment-18.0.1.0.0.9.dist-info/top_level.txt
odoo_addon_stock_picking_product_assortment-18.0.1.0.0.9.dist-info/RECORD
