Metadata-Version: 2.1
Name: odoo-addon-stock_picking_product_assortment
Version: 18.0.1.0.0.9
Requires-Python: >=3.10
Requires-Dist: odoo-addon-base_view_inheritance_extension==18.0.*
Requires-Dist: odoo-addon-product_assortment==18.0.*
Requires-Dist: odoo==18.0.*
Summary: Stock Picking Product Assortment
Home-page: https://github.com/OCA/stock-logistics-warehouse
License: AGPL-3
Author: Tecnativa, Odoo Community Association (OCA)
Author-email: support@odoo-community.org
Classifier: Programming Language :: Python
Classifier: Framework :: Odoo
Classifier: Framework :: Odoo :: 18.0
Classifier: License :: OSI Approved :: GNU Affero General Public License v3
